yta_google_drive_downloader/__init__.py
yta_google_drive_downloader/downloader.py
yta_google_drive_downloader/resource.py
yta_google_drive_downloader/utils.py
yta_google_drive_downloader-0.0.11.dist-info/licenses/LICENSE
yta_google_drive_downloader-0.0.11.dist-info/METADATA
yta_google_drive_downloader-0.0.11.dist-info/WHEEL
yta_google_drive_downloader-0.0.11.dist-info/RECORD
